geniusrise_prompt_actions/__init__.py
geniusrise_prompt_actions-0.1.0.dist-info/METADATA
geniusrise_prompt_actions-0.1.0.dist-info/WHEEL
geniusrise_prompt_actions-0.1.0.dist-info/top_level.txt
geniusrise_prompt_actions-0.1.0.dist-info/RECORD
